MarkerMAG/MarkerMAG_config.py
MarkerMAG/SILVA_16S_order.fasta
MarkerMAG/VERSION
MarkerMAG/__init__.py
MarkerMAG/barrnap_16s.py
MarkerMAG/filter_sam.py
MarkerMAG/get_cp_num.py
MarkerMAG/get_mag_depth.py
MarkerMAG/link_16s.py
MarkerMAG/matam_16s.py
MarkerMAG/polish_16s.py
MarkerMAG/recovery_16s.py
MarkerMAG/rename_reads.py
MarkerMAG/subsample_reads.py
MarkerMAG/uclust_16s.py
MarkerMAG/vxtractor/README.txt
MarkerMAG/vxtractor/gpl.txt
MarkerMAG/vxtractor/readmefungiLSU.txt
MarkerMAG/vxtractor/vxtractor.pl
MarkerMAG/vxtractor/HMMs/SSU_archaea/V1leftlong.HMM
MarkerMAG/vxtractor/HMMs/SSU_archaea/V1leftlong.HMM.h3f
MarkerMAG/vxtractor/HMMs/SSU_archaea/V1leftlong.HMM.h3i
MarkerMAG/vxtractor/HMMs/SSU_archaea/V1leftlong.HMM.h3m
MarkerMAG/vxtractor/HMMs/SSU_archaea/V1leftlong.HMM.h3p
MarkerMAG/vxtractor/HMMs/SSU_archaea/V1leftshort.HMM
MarkerMAG/vxtractor/HMMs/SSU_archaea/V1leftshort.HMM.h3f
MarkerMAG/vxtractor/HMMs/SSU_archaea/V1leftshort.HMM.h3i
MarkerMAG/vxtractor/HMMs/SSU_archaea/V1leftshort.HMM.h3m
MarkerMAG/vxtractor/HMMs/SSU_archaea/V1leftshort.HMM.h3p
MarkerMAG/vxtractor/HMMs/SSU_archaea/V1rightlong.HMM
MarkerMAG/vxtractor/HMMs/SSU_archaea/V1rightlong.HMM.h3f
MarkerMAG/vxtractor/HMMs/SSU_archaea/V1rightlong.HMM.h3i
MarkerMAG/vxtractor/HMMs/SSU_archaea/V1rightlong.HMM.h3m
MarkerMAG/vxtractor/HMMs/SSU_archaea/V1rightlong.HMM.h3p
MarkerMAG/vxtractor/HMMs/SSU_archaea/V1rightshort.HMM
MarkerMAG/vxtractor/HMMs/SSU_archaea/V1rightshort.HMM.h3f
MarkerMAG/vxtractor/HMMs/SSU_archaea/V1rightshort.HMM.h3i
MarkerMAG/vxtractor/HMMs/SSU_archaea/V1rightshort.HMM.h3m
MarkerMAG/vxtractor/HMMs/SSU_archaea/V1rightshort.HMM.h3p
MarkerMAG/vxtractor/HMMs/SSU_archaea/V2leftlong.HMM
MarkerMAG/vxtractor/HMMs/SSU_archaea/V2leftlong.HMM.h3f
MarkerMAG/vxtractor/HMMs/SSU_archaea/V2leftlong.HMM.h3i
MarkerMAG/vxtractor/HMMs/SSU_archaea/V2leftlong.HMM.h3m
MarkerMAG/vxtractor/HMMs/SSU_archaea/V2leftlong.HMM.h3p
MarkerMAG/vxtractor/HMMs/SSU_archaea/V2leftshort.HMM
MarkerMAG-1.1.28.dist-info/LICENSE.txt
MarkerMAG-1.1.28.dist-info/METADATA
MarkerMAG-1.1.28.dist-info/WHEEL
MarkerMAG-1.1.28.dist-info/top_level.txt
MarkerMAG-1.1.28.dist-info/RECORD
