Metadata-Version: 2.1
Name: MarkerMAG
Version: 1.1.28
Summary: linking MAGs with 16S rRNA marker genes
Home-page: https://pypi.org/project/MarkerMAG/
Author: Weizhi Song, Torsten Thomas
Author-email: songwz03@gmail.com
License: GPL3+
Keywords: Bioinformatics Metagenomics MAG 16S
Platform: UNKNOWN
Requires-Dist: biopython
Requires-Dist: pandas
Requires-Dist: plotly
Requires-Dist: seaborn
Requires-Dist: matplotlib
Requires-Dist: numpy
Requires-Dist: setuptools
